{"type":"FeatureCollection","features":[{"type":"Feature","geometry":{"type":"Point","coordinates":[0.09874702557902992,49.501544614530644]},"properties":{"title":"salut","description":"c furky","created_at":"2024-04-16T14:32:52.276Z"}}]}