{"type":"FeatureCollection","features":[{"type":"Feature","geometry":{"type":"Point","coordinates":[0.10144878301989024,49.49273583056703]},"properties":{"title":"test1","description":"test","created_at":"2024-04-16T14:30:03.446Z"}}]}